[{"id":1,"name":"生命","attributeId":1},{"id":2,"name":"力量","attributeId":3},{"id":3,"name":"防御","attributeId":4},{"id":4,"name":"魔力","attributeId":5},{"id":5,"name":"魔防","attributeId":6},{"id":6,"name":"暴击率","attributeId":9},{"id":7,"name":"怒气","attributeId":2},{"id":8,"name":"命中率","attributeId":7},{"id":9,"name":"回避率","attributeId":8},{"id":10,"name":"韧性","attributeId":10},{"id":11,"name":"暴击倍率","attributeId":11},{"id":12,"name":"暴击抗性","attributeId":12},{"id":13,"name":"治疗率","attributeId":13},{"id":14,"name":"治疗量","attributeId":14},{"id":15,"name":"受到治疗率","attributeId":15},{"id":16,"name":"受到治疗量","attributeId":16},{"id":17,"name":"物理免伤","attributeId":17},{"id":18,"name":"物理增伤","attributeId":18},{"id":19,"name":"法术免伤","attributeId":19},{"id":20,"name":"法术增伤","attributeId":20},{"id":21,"name":"物理穿透","attributeId":21},{"id":22,"name":"法术穿透","attributeId":22},{"id":23,"name":"极效治疗倍率","attributeId":23},{"id":24,"name":"中毒攻击","attributeId":24},{"id":25,"name":"禁疗攻击","attributeId":25},{"id":26,"name":"昏迷攻击","attributeId":26},{"id":27,"name":"沉默攻击","attributeId":27},{"id":28,"name":"衰弱攻击","attributeId":28},{"id":29,"name":"失明攻击","attributeId":29},{"id":30,"name":"固伤攻击","attributeId":30},{"id":31,"name":"中毒抗性","attributeId":31},{"id":32,"name":"禁疗抗性","attributeId":32},{"id":33,"name":"昏迷抗性","attributeId":33},{"id":34,"name":"沉默抗性","attributeId":34},{"id":35,"name":"衰弱抗性","attributeId":35},{"id":36,"name":"失明抗性","attributeId":36},{"id":37,"name":"固伤抗性","attributeId":37}]