[{"id":1,"attribute1":700,"attribute2":60,"attribute3":1,"attribute4":60,"attribute5":1,"attribute6":0,"attribute8":0,"attribute9":0,"attribute10":0,"attribute11":0,"attribute12":0,"attribute13":0,"attribute14":0,"attribute15":0,"attribute16":0,"attribute17":0,"attribute18":0,"attribute19":0,"attribute20":0,"attribute21":0,"attribute22":0,"attribute23":0,"attribute24":0,"attribute25":0,"attribute26":0,"attribute27":0,"attribute28":0,"attribute29":0,"attribute30":0,"attribute31":0,"attribute32":0,"attribute33":0,"attribute34":0,"attribute35":0,"attribute36":0,"attribute37":0},{"id":2,"attribute1":800,"attribute2":65,"attribute3":5,"attribute4":65,"attribute5":5,"attribute6":0,"attribute8":0,"attribute9":0,"attribute10":0,"attribute11":0,"attribute12":0,"attribute13":0,"attribute14":0,"attribute15":0,"attribute16":0,"attribute17":0,"attribute18":0,"attribute19":0,"attribute20":0,"attribute21":0,"attribute22":0,"attribute23":0,"attribute24":0,"attribute25":0,"attribute26":0,"attribute27":0,"attribute28":0,"attribute29":0,"attribute30":0,"attribute31":0,"attribute32":0,"attribute33":0,"attribute34":0,"attribute35":0,"attribute36":0,"attribute37":0},{"id":3,"attribute1":850,"attribute2":67,"attribute3":1,"attribute4":67,"attribute5":1,"attribute6":0,"attribute8":0,"attribute9":0,"attribute10":0,"attribute11":0,"attribute12":0,"attribute13":0,"attribute14":0,"attribute15":0,"attribute16":0,"attribute17":0,"attribute18":0,"attribute19":0,"attribute20":0,"attribute21":0,"attribute22":0,"attribute23":0,"attribute24":0,"attribute25":0,"attribute26":0,"attribute27":0,"attribute28":0,"attribute29":0,"attribute30":0,"attribute31":0,"attribute32":0,"attribute33":0,"attribute34":0,"attribute35":0,"attribute36":0,"attribute37":0},{"id":4,"attribute1":900,"attribute2":60,"attribute3":11,"attribute4":60,"attribute5":11,"attribute6":0,"attribute8":0,"attribute9":0,"attribute10":0,"attribute11":0,"attribute12":0,"attribute13":0,"attribute14":0,"attribute15":0,"attribute16":0,"attribute17":0,"attribute18":0,"attribute19":0,"attribute20":0,"attribute21":0,"attribute22":0,"attribute23":0,"attribute24":0,"attribute25":0,"attribute26":0,"attribute27":0,"attribute28":0,"attribute29":0,"attribute30":0,"attribute31":0,"attribute32":0,"attribute33":0,"attribute34":0,"attribute35":0,"attribute36":0,"attribute37":0},{"id":5,"attribute1":5000,"attribute2":110,"attribute3":35,"attribute4":110,"attribute5":35,"attribute6":0,"attribute8":0,"attribute9":0,"attribute10":0,"attribute11":0,"attribute12":0,"attribute13":0,"attribute14":0,"attribute15":0,"attribute16":0,"attribute17":0,"attribute18":0,"attribute19":0,"attribute20":0,"attribute21":0,"attribute22":0,"attribute23":0,"attribute24":0,"attribute25":0,"attribute26":0,"attribute27":0,"attribute28":0,"attribute29":0,"attribute30":0,"attribute31":0,"attribute32":0,"attribute33":99999,"attribute34":99999,"attribute35":0,"attribute36":0,"attribute37":0,"attributeGrow":[[43,0],[44,99999],[45,0],[46,99999]]},{"id":6,"attribute1":700,"attribute2":40,"attribute3":10,"attribute4":30,"attribute5":15,"attribute6":0,"attribute8":0,"attribute9":0,"attribute10":0,"attribute11":0,"attribute12":0,"attribute13":0,"attribute14":0,"attribute15":0,"attribute16":0,"attribute17":0,"attribute18":0,"attribute19":0,"attribute20":0,"attribute21":0,"attribute22":0,"attribute23":0,"attribute24":0,"attribute25":0,"attribute26":0,"attribute27":0,"attribute28":0,"attribute29":0,"attribute30":0,"attribute31":0,"attribute32":0,"attribute33":0,"attribute34":0,"attribute35":0,"attribute36":0,"attribute37":0},{"id":7,"attribute1":800,"attribute2":40,"attribute3":5,"attribute4":30,"attribute5":5,"attribute6":0,"attribute8":0,"attribute9":0,"attribute10":0,"attribute11":0,"attribute12":0,"attribute13":0,"attribute14":0,"attribute15":0,"attribute16":0,"attribute17":0,"attribute18":0,"attribute19":0,"attribute20":0,"attribute21":0,"attribute22":0,"attribute23":0,"attribute24":0,"attribute25":0,"attribute26":0,"attribute27":0,"attribute28":0,"attribute29":0,"attribute30":0,"attribute31":0,"attribute32":0,"attribute33":0,"attribute34":0,"attribute35":0,"attribute36":0,"attribute37":0},{"id":8,"attribute1":850,"attribute2":40,"attribute3":5,"attribute4":30,"attribute5":8,"attribute6":0,"attribute8":0,"attribute9":0,"attribute10":0,"attribute11":0,"attribute12":0,"attribute13":0,"attribute14":0,"attribute15":0,"attribute16":0,"attribute17":0,"attribute18":0,"attribute19":0,"attribute20":0,"attribute21":0,"attribute22":0,"attribute23":0,"attribute24":0,"attribute25":0,"attribute26":0,"attribute27":0,"attribute28":0,"attribute29":0,"attribute30":0,"attribute31":0,"attribute32":0,"attribute33":0,"attribute34":0,"attribute35":0,"attribute36":0,"attribute37":0},{"id":9,"attribute1":900,"attribute2":40,"attribute3":5,"attribute4":30,"attribute5":5,"attribute6":0,"attribute8":0,"attribute9":0,"attribute10":0,"attribute11":0,"attribute12":0,"attribute13":0,"attribute14":0,"attribute15":0,"attribute16":0,"attribute17":0,"attribute18":0,"attribute19":0,"attribute20":0,"attribute21":0,"attribute22":0,"attribute23":0,"attribute24":0,"attribute25":0,"attribute26":0,"attribute27":0,"attribute28":0,"attribute29":0,"attribute30":0,"attribute31":0,"attribute32":0,"attribute33":0,"attribute34":0,"attribute35":0,"attribute36":0,"attribute37":0},{"id":10,"attribute1":700,"attribute2":40,"attribute3":11,"attribute4":30,"attribute5":11,"attribute6":0,"attribute8":0,"attribute9":0,"attribute10":0,"attribute11":0,"attribute12":0,"attribute13":0,"attribute14":0,"attribute15":0,"attribute16":0,"attribute17":0,"attribute18":0,"attribute19":0,"attribute20":0,"attribute21":0,"attribute22":0,"attribute23":0,"attribute24":0,"attribute25":0,"attribute26":0,"attribute27":0,"attribute28":0,"attribute29":0,"attribute30":0,"attribute31":0,"attribute32":0,"attribute33":0,"attribute34":0,"attribute35":0,"attribute36":0,"attribute37":0},{"id":11,"attribute1":800,"attribute2":40,"attribute3":11,"attribute4":30,"attribute5":11,"attribute6":0,"attribute8":0,"attribute9":0,"attribute10":0,"attribute11":0,"attribute12":0,"attribute13":0,"attribute14":0,"attribute15":0,"attribute16":0,"attribute17":0,"attribute18":0,"attribute19":0,"attribute20":0,"attribute21":0,"attribute22":0,"attribute23":0,"attribute24":0,"attribute25":0,"attribute26":0,"attribute27":0,"attribute28":0,"attribute29":0,"attribute30":0,"attribute31":0,"attribute32":0,"attribute33":0,"attribute34":0,"attribute35":0,"attribute36":0,"attribute37":0},{"id":12,"attribute1":850,"attribute2":40,"attribute3":11,"attribute4":30,"attribute5":11,"attribute6":0,"attribute8":0,"attribute9":0,"attribute10":0,"attribute11":0,"attribute12":0,"attribute13":0,"attribute14":0,"attribute15":0,"attribute16":0,"attribute17":0,"attribute18":0,"attribute19":0,"attribute20":0,"attribute21":0,"attribute22":0,"attribute23":0,"attribute24":0,"attribute25":0,"attribute26":0,"attribute27":0,"attribute28":0,"attribute29":0,"attribute30":0,"attribute31":0,"attribute32":0,"attribute33":0,"attribute34":0,"attribute35":0,"attribute36":0,"attribute37":0},{"id":20,"attribute1":4500,"attribute2":128,"attribute3":35,"attribute4":128,"attribute5":35,"attribute6":200,"attribute8":0,"attribute9":100,"attribute10":0,"attribute11":0,"attribute12":0,"attribute13":0,"attribute14":0,"attribute15":0,"attribute16":0,"attribute17":0,"attribute18":0,"attribute19":0,"attribute20":0,"attribute21":0,"attribute22":0,"attribute23":0,"attribute24":0,"attribute25":0,"attribute26":0,"attribute27":0,"attribute28":0,"attribute29":0,"attribute30":0,"attribute31":0,"attribute32":0,"attribute33":99999,"attribute34":99999,"attribute35":0,"attribute36":0,"attribute37":0,"attributeGrow":[[43,0],[44,99999],[45,0],[46,99999]]},{"id":21,"attribute1":4100,"attribute2":102,"attribute3":12,"attribute4":102,"attribute5":12,"attribute6":100,"attribute8":0,"attribute9":0,"attribute10":0,"attribute11":0,"attribute12":0,"attribute13":0,"attribute14":0,"attribute15":0,"attribute16":0,"attribute17":0,"attribute18":0,"attribute19":0,"attribute20":0,"attribute21":0,"attribute22":0,"attribute23":0,"attribute24":0,"attribute25":0,"attribute26":0,"attribute27":0,"attribute28":0,"attribute29":0,"attribute30":0,"attribute31":0,"attribute32":0,"attribute33":0,"attribute34":0,"attribute35":0,"attribute36":0,"attribute37":0},{"id":22,"attribute1":4500,"attribute2":100,"attribute3":42,"attribute4":100,"attribute5":42,"attribute6":0,"attribute8":0,"attribute9":0,"attribute10":0,"attribute11":0,"attribute12":0,"attribute13":0,"attribute14":0,"attribute15":0,"attribute16":0,"attribute17":0,"attribute18":0,"attribute19":0,"attribute20":0,"attribute21":0,"attribute22":0,"attribute23":0,"attribute24":0,"attribute25":0,"attribute26":0,"attribute27":0,"attribute28":0,"attribute29":0,"attribute30":0,"attribute31":0,"attribute32":0,"attribute33":0,"attribute34":0,"attribute35":0,"attribute36":0,"attribute37":0},{"id":23,"attribute1":4700,"attribute2":158,"attribute3":18,"attribute4":158,"attribute5":18,"attribute6":260,"attribute8":0,"attribute9":0,"attribute10":0,"attribute11":0,"attribute12":0,"attribute13":0,"attribute14":0,"attribute15":0,"attribute16":0,"attribute17":0,"attribute18":0,"attribute19":0,"attribute20":0,"attribute21":0,"attribute22":0,"attribute23":0,"attribute24":0,"attribute25":0,"attribute26":0,"attribute27":0,"attribute28":0,"attribute29":0,"attribute30":0,"attribute31":0,"attribute32":0,"attribute33":0,"attribute34":0,"attribute35":0,"attribute36":0,"attribute37":0},{"id":24,"attribute1":500,"attribute2":122,"attribute3":2,"attribute4":122,"attribute5":2,"attribute6":111,"attribute8":0,"attribute9":0,"attribute10":0,"attribute11":0,"attribute12":0,"attribute13":0,"attribute14":0,"attribute15":0,"attribute16":0,"attribute17":0,"attribute18":0,"attribute19":0,"attribute20":0,"attribute21":0,"attribute22":0,"attribute23":0,"attribute24":0,"attribute25":0,"attribute26":0,"attribute27":0,"attribute28":0,"attribute29":0,"attribute30":0,"attribute31":0,"attribute32":0,"attribute33":0,"attribute34":0,"attribute35":0,"attribute36":0,"attribute37":0},{"id":25,"attribute1":1200,"attribute2":112,"attribute3":19,"attribute4":112,"attribute5":19,"attribute6":0,"attribute8":0,"attribute9":0,"attribute10":0,"attribute11":0,"attribute12":0,"attribute13":0,"attribute14":0,"attribute15":0,"attribute16":0,"attribute17":0,"attribute18":0,"attribute19":0,"attribute20":0,"attribute21":0,"attribute22":0,"attribute23":0,"attribute24":0,"attribute25":0,"attribute26":0,"attribute27":0,"attribute28":0,"attribute29":0,"attribute30":0,"attribute31":0,"attribute32":0,"attribute33":0,"attribute34":0,"attribute35":0,"attribute36":0,"attribute37":0},{"id":26,"attribute1":1000000,"attribute2":200,"attribute3":0,"attribute4":200,"attribute5":0,"attribute6":0,"attribute8":0,"attribute9":0,"attribute10":0,"attribute11":0,"attribute12":0,"attribute13":0,"attribute14":0,"attribute15":0,"attribute16":0,"attribute17":0,"attribute18":0,"attribute19":0,"attribute20":0,"attribute21":0,"attribute22":0,"attribute23":0,"attribute24":0,"attribute25":0,"attribute26":0,"attribute27":0,"attribute28":0,"attribute29":0,"attribute30":0,"attribute31":0,"attribute32":0,"attribute33":0,"attribute34":0,"attribute35":0,"attribute36":0,"attribute37":0}]